setup.py
JscorpVite/__init__.py
JscorpVite/admin.py
JscorpVite/apps.py
JscorpVite/models.py
JscorpVite/tests.py
JscorpVite/views.py
JscorpVite.egg-info/PKG-INFO
JscorpVite.egg-info/SOURCES.txt
JscorpVite.egg-info/dependency_links.txt
JscorpVite.egg-info/requires.txt
JscorpVite.egg-info/top_level.txt
JscorpVite/migrations/__init__.py
JscorpVite/templatetags/__init__.py
JscorpVite/templatetags/vite.py