Metadata-Version: 2.1
Name: JscorpVite
Version: 1.0.3
Requires-Dist: Django
